MANIFEST.in
README.rst
setup.py
docs/HISTORY.txt
ftw/__init__.py
ftw.copymovepatches.egg-info/PKG-INFO
ftw.copymovepatches.egg-info/SOURCES.txt
ftw.copymovepatches.egg-info/dependency_links.txt
ftw.copymovepatches.egg-info/entry_points.txt
ftw.copymovepatches.egg-info/namespace_packages.txt
ftw.copymovepatches.egg-info/not-zip-safe
ftw.copymovepatches.egg-info/requires.txt
ftw.copymovepatches.egg-info/top_level.txt
ftw/copymovepatches/__init__.py
ftw/copymovepatches/cmfcatalogaware.py
ftw/copymovepatches/configure.zcml
ftw/copymovepatches/dx_copy_flags.py
ftw/copymovepatches/testing.py
ftw/copymovepatches/utils.py
ftw/copymovepatches/tests/__init__.py
ftw/copymovepatches/tests/builders.py
ftw/copymovepatches/tests/profiles.zcml
ftw/copymovepatches/tests/test_dexterity_copy_flags.py
ftw/copymovepatches/tests/test_move_rename.py
ftw/copymovepatches/tests/test_move_updates_date_date.py
ftw/copymovepatches/tests/test_move_updates_modified_date.py
ftw/copymovepatches/tests/profiles/default/types.xml
ftw/copymovepatches/tests/profiles/default/types/DXContainer.xml